rohmu/__init__.py
rohmu/atomic_opener.py
rohmu/compat.py
rohmu/compressor.py
rohmu/dates.py
rohmu/encryptor.py
rohmu/errors.py
rohmu/factory.py
rohmu/filewrap.py
rohmu/inotify.py
rohmu/py.typed
rohmu/rohmufile.py
rohmu/snappyfile.py
rohmu/transfer_pool.py
rohmu/typing.py
rohmu/util.py
rohmu/version.py
rohmu/zstdfile.py
rohmu/common/__init__.py
rohmu/common/constants.py
rohmu/common/models.py
rohmu/common/statsd.py
rohmu/common/strenum.py
rohmu/delta/__init__.py
rohmu/delta/common.py
rohmu/delta/snapshot.py
rohmu/notifier/__init__.py
rohmu/notifier/http.py
rohmu/notifier/interface.py
rohmu/notifier/logger.py
rohmu/notifier/null.py
rohmu/object_storage/__init__.py
rohmu/object_storage/azure.py
rohmu/object_storage/base.py
rohmu/object_storage/config.py
rohmu/object_storage/google.py
rohmu/object_storage/local.py
rohmu/object_storage/s3.py
rohmu/object_storage/sftp.py
rohmu/object_storage/swift.py
rohmu-2.7.0.dist-info/METADATA
rohmu-2.7.0.dist-info/WHEEL
rohmu-2.7.0.dist-info/licenses/LICENSE
rohmu-2.7.0.dist-info/RECORD
