Metadata-Version: 2.3
Name: rohmu
Version: 2.7.0
Summary: Rohmu is a python library providing an interface to various cloud storage providers.
Project-URL: Source Repository, https://github.com/Aiven-Open/rohmu/
Author-email: Aiven <opensource@aiven.io>
License: Apache-2.0 license
License-File: LICENSE
Classifier: Development Status :: 5 - Production/Stable
Classifier: Intended Audience :: Developers
Classifier: Intended Audience :: Information Technology
Classifier: Intended Audience :: System Administrators
Classifier: License :: OSI Approved :: Apache Software License
Classifier: Programming Language :: Python :: 3.8
Classifier: Programming Language :: Python :: 3.9
Classifier: Programming Language :: Python :: 3.10
Classifier: Programming Language :: Python :: 3.11
Classifier: Programming Language :: Python :: 3.12
Classifier: Topic :: Database :: Database Engines/Servers
Classifier: Topic :: Software Development :: Libraries :: Python Modules
Requires-Python: >=3.8
Requires-Dist: azure-common<2,>=1.1.28
Requires-Dist: azure-storage-blob>=2.1.0
Requires-Dist: botocore
Requires-Dist: cryptography
Requires-Dist: google-api-python-client
Requires-Dist: httplib2
Requires-Dist: oauth2client
Requires-Dist: paramiko
Requires-Dist: pydantic>=1.10.17
Requires-Dist: python-dateutil
Requires-Dist: python-snappy
Requires-Dist: python-swiftclient
Requires-Dist: requests
Requires-Dist: typing-extensions; python_version < '3.12'
Requires-Dist: zstandard
Provides-Extra: dev
Requires-Dist: boto3-stubs[s3]; extra == 'dev'
Requires-Dist: botocore; extra == 'dev'
Requires-Dist: google-api-python-client-stubs; extra == 'dev'
Requires-Dist: mypy==1.9.0; extra == 'dev'
Requires-Dist: pytest; extra == 'dev'
Requires-Dist: pytest-asyncio; extra == 'dev'
Requires-Dist: pytest-cov; extra == 'dev'
Requires-Dist: pytest-mock; extra == 'dev'
Requires-Dist: pytest-timeout; extra == 'dev'
Requires-Dist: python-snappy==0.6.1; extra == 'dev'
Requires-Dist: rstfmt; extra == 'dev'
Requires-Dist: ruff==0.3.3; extra == 'dev'
Requires-Dist: types-httplib2; extra == 'dev'
Requires-Dist: types-mock; extra == 'dev'
Requires-Dist: types-paramiko; extra == 'dev'
Requires-Dist: types-python-dateutil; extra == 'dev'
Requires-Dist: types-requests; extra == 'dev'
Requires-Dist: typing-extensions<5,>=3.10; (python_version < '3.12') and extra == 'dev'
Requires-Dist: zstandard==0.21.0; extra == 'dev'
Provides-Extra: docs
Requires-Dist: autodoc-pydantic==1.9.0; extra == 'docs'
Requires-Dist: sphinx-rtd-theme==1.0.0; extra == 'docs'
Requires-Dist: sphinx==5.3.0; extra == 'docs'
